dwani/__init__.py
dwani/asr.py
dwani/audio.py
dwani/chat.py
dwani/client.py
dwani/docs.py
dwani/exceptions.py
dwani/translate.py
dwani/vision.py
dwani-0.1.23.dist-info/licenses/LICENSE
dwani-0.1.23.dist-info/METADATA
dwani-0.1.23.dist-info/WHEEL
dwani-0.1.23.dist-info/top_level.txt
dwani-0.1.23.dist-info/RECORD
