Metadata-Version: 2.4
Name: dwani
Version: 0.1.23
Summary: Document Analytics + Multimodal API for Indian + European languages (Chat, Vision, TTS, ASR, Translate, Docs)
Author-email: sachin <python@dwani.ai>
License: MIT License
Project-URL: Homepage, https://github.com/dwani-ai/dwani-python-sdk
Project-URL: Source, https://github.com/dwani-ai/dwani-python-sdk
Project-URL: Issues, https://github.com/dwani-ai/dwani-python-sdk/issues
Requires-Python: >=3.8
License-File: LICENSE
Requires-Dist: requests>=2.25.0
Requires-Dist: openai
Dynamic: license-file
